LICENSE
jtran/__init__.py
jtran/jtran.py
jtran/translation_maps.py
jtran-0.2.13.dist-info/LICENSE
jtran-0.2.13.dist-info/WHEEL
jtran-0.2.13.dist-info/METADATA
jtran-0.2.13.dist-info/RECORD
