Metadata-Version: 2.1
Name: jtran
Version: 0.2.13
Summary: Japanese kana-latin transliteration tables
Home-page: https://github.com/kateabr/jtran
License: MIT
Author: Ekaterina Biryukova
Author-email: kateabr@yandex.ru
Requires-Python: >=3.5,<4.0
Classifier: License :: OSI Approved :: MIT License
Classifier: Programming Language :: Python :: 3
Classifier: Programming Language :: Python :: 3.5
Classifier: Programming Language :: Python :: 3.6
Classifier: Programming Language :: Python :: 3.7
Classifier: Programming Language :: Python :: 3.8
Classifier: Programming Language :: Python :: 3.9
Classifier: Programming Language :: Python :: Implementation :: CPython
Project-URL: Repository, https://github.com/kateabr/jtran
